we_love/alfred/__init__.py
we_love_alfred-0.5.1.dist-info/WHEEL
we_love_alfred-0.5.1.dist-info/METADATA
we_love_alfred-0.5.1.dist-info/RECORD
