Metadata-Version: 2.3
Name: we-love-alfred
Version: 0.5.1
Summary: help make alfred commands nice for we-love namespace
Requires-Dist: favicon
Requires-Dist: pydantic>=2
Requires-Dist: httpx
Requires-Dist: aiopath
Requires-Python: >=3.13
